{
	"영화": {
		"감독": {
			"count": 1024,
			"questions": [
				"(S)를 만든 (P)의 이름은 무엇인가요?",
				"(S)의 연출가는 누구일까요?",
				"(S)라는 영화는 누가 만들었나요?",
				"(S)는 누가 만들었어요?",
				"(S)라는 영화를 제작한 이는 누구인가요?",
				"(S)에서 (P)를 누구 맡았나요?",
				"Captain America: The Winter Soldier를 제작한 (P)는 누구에요?",
				"(S) 의 (P)는 누구인가요?",
				"어떤 사람이 (S)의 (P)인가요?",
				"(S)의 (P)의 이름을 적어주세요.",
				"영화 (S)의 (P)는 누구일까요?",
				"(S)가라는 제목의 영화를 만든 (P)는 누구인가요?",
				"(S)의 제작을 총괄하신분은 누구인가요?",
				"누가 (S)의 (P)인가요?",
				"(S)를 진두지휘한 사람은 누구인가요?",
				"누가 (S)를 연출했나요?",
				"(S)의 촬영을 지휘한 사람이 누구인가요?",
				"(S)의 제작자는 누구인가요?",
				"(S)의 (P)가름은 무엇인가요?",
				"(S)는 누가 (P)를 했나요?",
				"(S)2011년 영화는 누가 만들었나요?",
				"(S)의 모든것을 총괄한 사람은 누구인가요?",
				"(S)(P)가 누군지 알면 알려주시지요",
				"(S)는 누가 (P)인가요?",
				"(S)의 (P)는 누가 맡았을까요?",
				"(S)를 총 (P)한 사람은 누구인가요?",
				"(S)를 (P)한 사람은 어떤 사람이 (P)했을까요?",
				"(S)는 어떤 사람이 (P)를 맡았나요?",
				"(S)제작자는 누구인가요?",
				"(S)는 어떤 사람의 작품인가요?",
				"(S)의 연출가는 누구인가요?",
				"누가 (S)를 (P)했나요?",
				"(S)는 누가 만든작품인가요?",
				"(S)의 (P)가름은 무엇이에요?",
				"(S)가라는 영화의 (P)는 누구인가요?",
				"(S)에서 메가폰을 잡은 사람은 누군가요?",
				"(S)를 (P)한 인물은 누구인가요?",
				"(S)를 제작한 사람은 어떤 사람인가요?",
				"어떤 (P)가 (S)를 만들었나요?",
				"영화 중에 (S)의 (P)가 누군가요",
				"(S)를 총지휘한 (P)는 누구인가요?",
				"(S)를 찍은 사람이 누구예요?",
				"(S)에서 (P)직은 누가 맡았나요?",
				"여자 정혜의 (P)는 누구에요?",
				"(S)는 누가 연출했나요?",
				"(S)영화는 누가 만들었나요?",
				"누가 (S)라는 영화를 만들었나요?",
				"(S)(P)가름은 무엇이에요?",
				"누가 (S)를 지휘해서 만들었나요?",
				"(S)(1984년 영화은 누가 연출했나요?",
				"영화 (S)의 (P)가 누구인지 아시면 알려주세요",
				"이 영화 (S)를 제작한 사람은 누구인가요?",
				"영화 (S)를 제작한 사람은 누구인가요?",
				"영화 (S)를 (P)한 사람의 이름은 무엇인가요?",
				"(S)를 연출한 사람은 누구인가요?",
				"(S)를 만든 사람은 누구인가요?",
				"누가 (S)의 (P)를 맡았나요?",
				"영화 (S)는 누가 (P)인가요?",
				"2014년 영화 (S)는 누가 (P)했나요?",
				"(S)를 (P)한 사람이 누구예요?",
				"(S)를 제작한 (P)는 누구에요?",
				"(S)는 누가 디렉팅했나요?",
				"(S)의 디렉터는 누구인가요?",
				"(S)는 어떤 (P)가 메가폰을 잡았나요?",
				"(S)의 (P)를 맡은 사람이 누구일까요?",
				"(S)를 제작한 사람은 누구인가요?",
				"누가 (S)를 총 지휘했나요?",
				"(S)v의 (P)의 이름은 무엇인가요?",
				"(S)는 어느 (P)의 작품이에요?",
				"누가 (S)를 만들었나요?",
				"(S)를 제작한 (P)는 누구인가요?",
				"(S)에서 (P)를 맡은 인물은 누구인가요?",
				"(S)(P)의 이름이 어떻게 되나요?",
				"(S)(P)는 누구예요?",
				"(S)의 (P)는 누구예요?",
				"(S)는 누가 제작했나요?",
				"(S)를 만든 (P)의 이름은 누구일까요?",
				"2008년 영화 (S)를 만든 사람은 누구인가요?",
				"영화 (S)는 어떤 (P)가 제작했나요?",
				"(S)는 어느 (P)의 영화인가요?",
				"(S)를 총 지휘한 사람의 이름은 무엇인가요?",
				"DMZ비무장지대를 연출한 사람은 누구예요?",
				"(S)의 (P)를 알고 싶어요.",
				"(S)를 만든 (P)는 누구인가요?",
				"(S)라는 2011년 영화를 만든 사람은 누구인가요?",
				"(S)은 누가 만들었나요?",
				"(S)를 찍은 (P)는 누구인가요?",
				"(S)는 누가 총 지휘했나요?",
				"(S)는 누가 (P)하였나요?",
				"(S)는 어떤 (P)의 작품인가요?",
				"DMZ 비무장지대의 (P)를 맡은 사람은 누구인가요?",
				"(S)의 (P)는 누가 했나요?",
				"(S)의 디렉터가 누구인가요?",
				"(S)는 누가 지휘해서 만들었나요?",
				"(S)를 만들고 지휘한 사람은 누구인가요?",
				"영화 (S)의 (P)는 누구인가요?",
				"(S)는 (P)누가 연출했나요?",
				"(S)의 (P)가 누군지 아시는지요?",
				"영화 (S)를 만든 (P)가름은 무엇인가요?",
				"영화 (S)는 누가 만들었나요?",
				"(S)(P)는 어떻게 되나요?",
				"(S)제작을 총괄해서 맡은 사람은 누구인가요?",
				"(S)라는 영화는 누구의 작품인가요?",
				"(S)는 누구의 지휘 아래에 만들어진 영화인가요?",
				"(S)를 (P)한 사람의 이름은 무엇인가요?",
				"(S)를 총 지휘한 사람은 누구인가요?",
				"(S)는 어떤 (P)가 연출했나요?",
				"(S)를 만든사람은 누구인가요?",
				"(S)v의 (P)의 이름을 답해주세요.",
				"(S)는 누구의 지휘아래 만들어졌나요?",
				"(S)는 누가 연출을 맡았나요?",
				"(S)의 메가폰을 잡은 사람은 누구인가요?",
				"(S)의 (P)가름을 쓰세요.",
				"(S)는 누구의 작품인가요?",
				"로봇소리를 만든 사람은 누구인가요?",
				"누가 영화 (S)의 (P)를 담당했나요?",
				"영화 (S)의 (P)를 누가 맡았나요?",
				"(S)의 (P)를 맡은 사람은 누구인가요?",
				"(S)를 (P)한 사람이 누구인가요?",
				"(S)의 (P)의 이름은 무엇인가요?",
				"(S)는 누가 (P)한 영화인가요?",
				"(S)는 누가 (P)했나요?",
				"(S)는 어느 (P)의 작품인가요?",
				"(S)제작한 사람은 누구인가요?",
				"(S)를 찍은 (P)는 누구예요?",
				"(S)를 (P)한 사람은 누구였나요?",
				"(S)를 지휘하여 촬영한 사람은 누구인가요?",
				"(S)2008년 영화는 누가 만들었나요?",
				"(S)의 (P)를 누가했나요?",
				"(S)의 연출이 누구에요?",
				"(S)를 누가 만들었나요?",
				"(S)는 어떤 사람이 만들었나요?",
				"(S)의 영화제작을 지휘하시는 분은 누구인가요?",
				"(S)는 어느 (P)가 만들었나요?",
				"(S)는 누가 (P)를 맡았나요?",
				"(S)를 누가 진두지휘 하셨나요?",
				"(S)(P)는 누가 맡았나요?",
				"(S)를 총괄하고 책임진 사람은 누구인가요?",
				"(S)를 지휘하며 촬영한 사람은 누구인가요?",
				"여자 정혜의 (P)를 누가했는지 알아요?",
				"(S)는 누구의 (P)으로 찍은 건가요?",
				"(S)의 (P)를 알려주세요.",
				"(S)를 (P)한 사람은 누구인가요?",
				"(S)(P)의 이름은 무엇인가요?",
				"(S)라는 영화(P)으로 유명한 사람은 누구인가요?",
				"(S)의 (P)님의 성함은 무엇인가요?",
				"로봇소리의 제작 과정을 책임진 사람은 누구인가요?",
				"영화 (S)의 (P)가 누군지 아시나요?",
				"2012년에 나온 (S)를 찍은 (P)가 누구예요?",
				"(S)를 만든 사람은 누구에요?",
				"(S)의 제작을 지휘한 사람은 누구인가요?",
				"누가 영화 (S)의 (P)가에요?",
				"영화 (S)의 (P)님의 성함은 무엇인가요?",
				"영화 (S)(P)가 누군지 아시는지요?",
				"애니메이션 (S)의 (P)가 누구인가요?",
				"(S)의 (P)를 담당한 사람은 누구인가요?",
				"(S)의 (P)는 어떻게 되요?",
				"(S)는 누가 만들었나요?",
				"(S)를 지휘해서 만든 사람은 누구인가요?"
			],
			"answers": [
				"(S)를 만든 사람은 (O)(P)가에요.",
				"(S)는 (O)가 (P)했어요.",
				"(S)는 (O)가 (P)를 맡았어요.",
				"(S)라는 영화는 (O)가 만들었어요.",
				"(O)가 (S)를 제작했어요",
				"영화 (S)는 (O)가 (P)를 맡았어요.",
				"영화 (S)를 제작한 사람은 (O)에요.",
				"(S)는 신수원 홍지영 이수연 김성호가 (P)를 맡은 영화라고 해요",
				"(S)를 (O)가 (P)했어요.",
				"(O)가라는 사람이 (S)를 (P)했어요.",
				"(S)를 만든 (P)의 이름은 (O)가에요.",
				"(O)(P)가 (S)를 (P)했어요.",
				"(S)의 (P)가름은 (O)가라고 해요",
				"(S)를 총괄하고 책임진 사람은 (O)에요.",
				"(S)는 (O)(P)의 작품이에요.",
				"(S)라는 (O)가 만든 영화에요.",
				"DMZ비무장지대의 (P)를 맡은 사람은 (O)가에요",
				"(S)는 (O)가 (P)를 한 영화예요.",
				"(S)(P)의 이름은 (O)가에요.",
				"(S)에요.",
				"(S)의 디렉터는 (O)에요",
				"여자 정혜를 찍은 (P)님은 (O)(P)님인 걸로 알고 있어요",
				"(S)를 총괄하고 책임진 사람은 (O)가에요.",
				"(S)를 만든 (P)는 (O)에요",
				"(S)를 제작한 사람은 (O)라고 해요.",
				"(S)라는 영화를 제작한 이는 (O)에요.",
				"(S)는 (O)가 (P)해요",
				"(S)가라는 영화의 (P)는 (O)가에요.",
				"영화 (S)의 (P)는 (O)가에요.",
				"(S)v의 (P)가름은 (O)라고 해요.",
				"(S)는 (O)라는 사람이 (P)했어요.",
				"(S)는 (O)가라는 사람이 (P)가에요.",
				"(S)2011년 영화를 만든 사람은 (O)가에요.",
				"(S)의 연출을 맡은 사람은 (O)가에요.",
				"(S)의 제작자는 (O)가에요.",
				"(S)(P)를 한 사람은 (O)가에요",
				"영화 (S)를 제작한 사람은 (O)가에요.",
				"(S)의 (P)는 (O)라지요",
				"(S)의 (P)가름은 (O)예요.",
				"신수원 홍지영 이수연 김성호는 (S)의 (P)가라고 해요",
				"(S)를 총괄한 분은 (O)가에요.",
				"(O)는 (S)의 (P)가라고 해요",
				"(S)를 만든 (P)는 (O)라고 해요.",
				"(S)를 총괄한 사람은 (O)가에요.",
				"2014년 영화 (S)는 (O)가 (P)가에요.",
				"(S)는 (O)가 만들었어요.",
				"(S)를 만든 사람은 (O)가에요.",
				"(O)(P)가 (S)의 (P)가에요.",
				"(S)는 (O)(P)가 만들었어요",
				"(S)를 만든 사람은 (O)에요.",
				"(S)의 (P)를 맡은 사람은 (O)가에요.",
				"(S)가 (P)한 영화예요.",
				"로봇소리를 만든 사람은 (O)에요.",
				"(S)는 신아가 이상철이 제작했어요.",
				"(S)의 (P)는 강경태 구교환이옥섭윤성호 예요.",
				"(O)(P)가 (S)의 메가폰을 잡았어요.",
				"영화 (S)의 (P)는 (O)라네요",
				"(S)는 (O)가 (P)가예요",
				"(S)를 지휘해서 만든 사람은 (O)에요.",
				"(S)에서 메가폰을 잡은 사람은 (O)가에요.",
				"(O)가 (S)를 총 지휘했어요.",
				"(S)(P)는 (O)가 맡았어요.",
				"(S)를 지휘해서 만든 사람은 (O)가에요.",
				"신아가 이상철은 (S)의 (P)가에요.",
				"(S)의 (P)는 (O)가에요.",
				"(S)를 지휘하여 촬영한 사람은 (O)가에요",
				"(O)가 (S)의 (P)가에요.",
				"(S)라는 영화는 (O)(P)가 만들었어요",
				"(S)는 (O)가 (P)했어요",
				"(S)주는 (O)가 (P)가예요",
				"(O)를 총 지휘했어요.",
				"(S)를 제작한 (P)는 (O)에요.",
				"(O)(P)가 (S)의 제작을 지휘한 사람이에요.",
				"(S)는 (O)가 (P)한 작품이에요.",
				"(S)의 (P)가름은 (O)에요.",
				"(S)(P)가름은 (O)가에요",
				"(S)를 연출한 사람은 (O)에요.",
				"(O)가 (S)를 (P)했어요",
				"(S)를 (P)한 사람은 (O)가에요.",
				"(S)는 (O)연출이 만들었어요.",
				"(O)는 (S)의 (P)가예요.",
				"(O)가 (S)의 (P)가예요",
				"로봇소리의 제작과정을 책임진 사람은 (O)에요.",
				"(O)는 (S)의 (P)가에요",
				"(S)는 (O)에의해 만들어졌어요",
				"(S)는 (O)(P)의 작품이라고 해요",
				"(O)(P)가 (S)의 촬영을 지휘했어요.",
				"(S)를 만든 사람은 (O)가에요",
				"(S)를 진두지휘 한 사람은 (O)예요",
				"(O)가 (S)를 제작했어요.",
				"(S)영화를 만든 사람은 (O)가에요.",
				"(S)2008년 영화는 (O)가 만들었어요.",
				"(S)를 제작한 사람은 (O)가에요.",
				"(S)는 (O)가 총 지휘했어요.",
				"(O)(P)는 (S)를 만들었어요",
				"(O)(P)가 (S)를 연출했어요.",
				"DMZ비무장지대를 연출한 (P)는 (O)가에요",
				"(S)를 (P)한 사람은 (O)가예요.",
				"(S)의 (P)직을 (O)가 맡았어요",
				"여자 정혜의 (P)는 (O)에요.",
				"(S)가라는 제목의 영화를 만든 (P)는 (O)가에요.",
				"(S)의 (P)가 된 사람은 (O)예요.",
				"(S)를 제작한 사람은 (O)(P)가에요",
				"(S)를 제작한 (P)는 (O)가에요.",
				"(S)는 (O)가 (P)가에요.",
				"(S)를 만든 영화 (P)는 (O)라고 해요.",
				"(S)제작자는 (O)가에요.",
				"(S)의 (P)가름은 (O)가에요.",
				"(O)(P)가 (S)를 만들었어요",
				"(S)의 모든것을 총괄한 사람은 (O)가에요",
				"(S)를 (P)한 사람은 (O)예요.",
				"(S)는 (O)(P)의 영화예요.",
				"(S)(O)(P)가 정사를 만들었어요.",
				"(S)의 (P)는 (O)가예요.",
				"2008년 영화 (S)를 만든 사람은 (O)가에요.",
				"(S)v를 만든 (P)는 (O)에요.",
				"(S)의 지휘하시는 분은 (O)에요",
				"(O)가 (S)의 (P)를 맡았어요.",
				"(S)를 (P)한 사람은 (O)에요.",
				"(S)의 연출가는 (O)에요.",
				"(S)가 만들었어요.",
				"(S)를 연출한 사람은 (O)(P)가에요.",
				"(S)영화의 (P)직을 맡은 인물은 (O)에요",
				"(S)의 (P)님 성함은 (O)가에요",
				"(S)를 진두지휘한 사람은 (O)가예요",
				"(O)는 (S)의 (P)가에요.",
				"(O)가 (S)를 연출했어요.",
				"(S)는 (O)가 (P)한거예요.",
				"(S)는 (O)가 연출했어요.",
				"(S)는 (O)가 (P)한 작품이에요",
				"(S)연출자는 (O)가에요.",
				"(S)를 지휘하며 촬영한 사람은 (O)가에요.",
				"(S)의 (P)는 이옥섭구교환강경태윤성호 예요.",
				"(O)가 영화 (S)의 (P)를 담당했어요.",
				"(S)의 (P)는 (O)가지요",
				"영화 (S)의 (P)는 (O)가에요",
				"(S)라는 2011년 영화는 (O)가 만들었어요.",
				"(O)영화(P)가 (S)를 연출했어요.",
				"(S)는 (O)(P)가 찍었어요.",
				"영화 (S)를 (P)한 사람의 이름은 (O)가에요.",
				"(O)는 (S)를 (P)했어요",
				"(S)는 (O)(P)가 만들었어요.",
				"(S)는 (O)가 지휘해서 만들었어요.",
				"(O)가 (S)의 (P)가에요",
				"(S)에서 (P)를 한 사람은 (O)가에요.",
				"(S)의 (P)는 (O)가라고 하지요",
				"(O)(P)가 (S)의 제작을 지휘했어요.",
				"(S)를 만든 사람 이름은 (O)가에요",
				"(O)가 (S)를 디렉팅했어요.",
				"(O)가 (S)를 (P)했어요.",
				"(S)의 (P)를 맡은 사람은 (O)에요.",
				"(S)는 (O)가 (P)를 했어요.",
				"(S)를 총 지휘한 사람의 이름은 (O)예요.",
				"(O)(P)가 (S)를 만들었어요.",
				"(S)((S)O(S))(S)를(S) (S)((S)P(S))(S)했(S)어(S)요(S).(S)",
				"김상민은 (S)라는 영화를 만들었어요.",
				"(O)가 (P)를 맡은 영화는 (S)가에요.",
				"(O)(P)는 (S)를 제작했어요.",
				"(S)을 만든 사람은 (O)(P)가에요.",
				"(O)(P)가 (S)를 찍었어요.",
				"(S)의 연출자는 (O)가에요.",
				"(S)를 제작한 김독의 이름은 (O)가예요.",
				"영화 (S)의 (P)는 (O)가라네요",
				"(O)는 (S)의 (P)했어요",
				"(S)는 (P)(O)의 작품이에요.",
				"(S)를 총 (P)한 사람은 (O)가에요.",
				"(S)라는 영화를 (P)한 사람은 (O)에요.",
				"(O)(P)의 영화는 (S)예요.",
				"(S)는 (O)가 만들었어요",
				"(S)에서 (P)를 맡은 인물은 (O)가에요",
				"(S)는 (O)(P)에 의해 제작되었어요.",
				"(S)의 연출은 (O)가 맡았어요.",
				"(S)에서 (O)는 (P)를 맡았어요.",
				"(S)은 (O)(P)가 만들었어요.",
				"영화 (S)에서 (O)가 (P)를 맡았어요",
				"(S)를 만든 (P)는 (O)라는 사람이에요.",
				"(O)는 영화 (S)의 (P)가예요.",
				"(S)를 지휘하며 촬영한 사람은 (O)에요."
			],
			"duplicates": [
				"(S)의 (P)는 (O)가예요.",
				"(O)가 (S)를 (P)했어요.",
				"(S)를 만든 사람은 누구인가요?",
				"(S)는 누가 (P)를 했나요?",
				"(S)의 연출가는 누구인가요?",
				"(S)는 (O)가 연출했어요.",
				"(S)의 연출가는 누구일까요?",
				"(O)(P)가 (S)를 연출했어요.",
				"(S)는 누가 만들었나요?",
				"(S)는 (O)(P)가 만들었어요",
				"(S)는 누가 만들었나요?",
				"(S)는 (O)(P)가 만들었어요.",
				"(O)가 (S)를 (P)했어요.",
				"(S)를 만든 사람은 누구인가요?",
				"(S)는 누가 만들었나요?",
				"(S)는 누가 (P)인가요?",
				"(S)는 누가 (P)했나요?",
				"(S)는 누구의 작품인가요?",
				"(S)를 지휘해서 만든 사람은 누구인가요?",
				"(S)는 (O)가 지휘해서 만들었어요.",
				"(S)는 누가 (P)했나요?",
				"(S)는 (O)가 만들었어요.",
				"(S)는 누가 (P)인가요?",
				"(O)(P)가 (S)를 (P)했어요.",
				"(S)는 (O)(P)가 만들었어요.",
				"(S)를 만든 사람은 누구인가요?",
				"2012년에 나온 (S)를 찍은 (P)가 누구예요?",
				"(S)는 (O)가 (P)를 한 영화예요.",
				"(S)는 누가 만들었나요?",
				"(S)는 (O)(P)가 만들었어요",
				"(S)는 (O)가 (P)를 맡았어요.",
				"(O)가 (S)를 (P)했어요.",
				"(S)의 (P)를 알려주세요.",
				"(S)를 (P)한 사람은 누구인가요?",
				"(S)를 (P)한 사람은 누구인가요?",
				"(S)를 (P)한 사람은 (O)가예요.",
				"(S)는 누가 총 지휘했나요?",
				"누가 (S)의 (P)를 맡았나요?",
				"(O)가 (S)의 (P)가에요.",
				"(S)는 누구의 작품인가요?",
				"(S)의 (P)가름은 무엇인가요?",
				"(S)의 (P)가름은 (O)예요.",
				"(S)는 누가 (P)했나요?",
				"(S)는 누구의 작품인가요?",
				"(S)는 (P)(O)의 작품이에요.",
				"(S)는 누가 (P)했나요?",
				"(S)는 (O)(P)의 영화예요.",
				"(S)는 누가 (P)인가요?",
				"(O)가 (S)의 (P)가에요.",
				"(O)가 (S)의 (P)가에요.",
				"(S)영화는 누가 만들었나요?",
				"(S)영화를 만든 사람은 (O)가에요.",
				"(S)는 누가 연출했나요?",
				"(S)는 (O)가 지휘해서 만들었어요.",
				"(S)는 누가 (P)했나요?",
				"(O)가 (S)의 (P)가에요",
				"(S)를 지휘해서 만든 사람은 누구인가요?",
				"(S)는 (O)가 지휘해서 만들었어요.",
				"(S)는 (O)가 (P)했어요",
				"(S)의 (P)는 어떻게 되요?",
				"(O)는 (S)의 (P)가예요.",
				"(S)는 (O)가 만들었어요.",
				"(S)는 누가 (P)인가요?",
				"(O)가 (S)의 (P)가에요.",
				"(S)를 제작한 (P)는 누구인가요?",
				"(S)를 제작한 (P)는 (O)에요.",
				"(S)는 (O)가 (P)가에요.",
				"(S)는 누가 지휘해서 만들었나요?",
				"(S)는 (O)가 지휘해서 만들었어요.",
				"(S)는 누가 만들었어요?",
				"(S)는 (O)가 만들었어요.",
				"영화 (S)는 누가 (P)인가요?",
				"(S)는 (O)(P)의 영화예요.",
				"(S)(P)는 어떻게 되나요?",
				"(O)는 영화 (S)의 (P)가예요.",
				"(S)는 누가 만들었어요?",
				"(S)는 (O)가 만들었어요.",
				"(S)의 (P)는 누구예요?",
				"(S)의 (P)는 (O)가예요.",
				"(S)는 누가 (P)인가요?",
				"(S)는 (O)가 (P)가에요.",
				"(S)를 지휘해서 만든 사람은 누구인가요?",
				"(S)는 (O)가 지휘해서 만들었어요.",
				"(S)는 누가 만들었어요?",
				"(S)는 (O)가 만들었어요.",
				"(S)를 총 (P)한 사람은 누구인가요?",
				"(S)를 총 (P)한 사람은 (O)가에요.",
				"(S)는 어느 (P)가 만들었나요?",
				"(O)(P)가 (S)를 만들었어요.",
				"(S)는 (O)가 (P)를 맡았어요.",
				"(S)라는 영화는 누가 만들었나요?",
				"(O)(P)가 (S)를 만들었어요.",
				"(S)를 제작한 (P)는 (O)에요.",
				"(S)를 만든 (P)의 이름은 무엇인가요?",
				"(S)를 만든 (P)의 이름은 (O)가에요.",
				"영화 (S)의 (P)님의 성함은 무엇인가요?",
				"(S)의 (P)님 성함은 (O)가에요",
				"(S)는 누가 만들었나요?",
				"누가 (S)의 (P)인가요?",
				"이 영화 (S)를 제작한 사람은 누구인가요?",
				"(S)를 제작한 사람은 (O)가에요.",
				"(S)를 만든 사람은 누구인가요?",
				"(S)를 만든 사람은 (O)가에요.",
				"(S)를 만든 (P)는 누구인가요?",
				"(S)에요.",
				"(S)를 만든 사람은 누구인가요?",
				"(S)를 만든 사람은 (O)(P)가에요.",
				"누가 (S)를 총 지휘했나요?",
				"(O)를 총 지휘했어요.",
				"(S)를 (P)한 사람이 누구예요?",
				"(O)(P)가 (S)를 (P)했어요.",
				"(S)는 어느 (P)의 작품인가요?",
				"(O)가 (S)의 (P)가에요",
				"(S)는 누가 (P)했나요?",
				"(S)를 총괄하고 책임진 사람은 누구인가요?",
				"(S)를 (P)한 사람이 누구예요?",
				"(S)를 (P)한 사람은 (O)가에요.",
				"누가 (S)의 (P)를 맡았나요?",
				"(S)의 (P)를 맡은 사람은 (O)에요.",
				"(S)는 어느 (P)의 작품인가요?",
				"(O)가 (S)의 (P)가에요",
				"(S)는 누가 만든작품인가요?",
				"(O)(P)가 (S)를 만들었어요",
				"(S)를 만든사람은 누구인가요?",
				"(O)(P)는 (S)를 만들었어요",
				"(S)는 누가 (P)하였나요?",
				"(O)는 (S)의 (P)가에요.",
				"(S)의 (P)는 누구예요?",
				"(S)의 (P)는 (O)가예요.",
				"누가 (S)의 (P)인가요?",
				"(O)가 (S)의 (P)가에요.",
				"누가 영화 (S)의 (P)를 담당했나요?",
				"(O)가 영화 (S)의 (P)를 담당했어요.",
				"(S)를 만든사람은 누구인가요?",
				"(O)(P)는 (S)를 만들었어요",
				"(S)를 제작한 (P)는 누구에요?",
				"(S)를 제작한 (P)는 (O)에요.",
				"누가 영화 (S)의 (P)가에요?",
				"(O)가 (S)의 (P)가에요.",
				"(S)를 (P)한 사람은 누구인가요?",
				"(O)는 (S)를 (P)했어요",
				"영화 (S)를 제작한 사람은 누구인가요?",
				"(S)를 만든 사람은 누구인가요?",
				"(O)는 (S)의 (P)가에요",
				"(O)는 (S)를 (P)했어요",
				"(S)는 누가 (P)했나요?",
				"(S)는 (O)가 (P)해요",
				"(S)는 누가 (P)를 했나요?",
				"(S)를 제작한 (P)는 누구에요?",
				"(S)는 누가 (P)인가요?",
				"(S)주는 (O)가 (P)가예요",
				"(S)는 누가 지휘해서 만들었나요?",
				"(S)를 지휘해서 만든 사람은 (O)에요.",
				"(S)의 (P)는 누구예요?",
				"(S)의 (P)는 (O)가예요.",
				"(S)를 연출한 사람은 누구인가요?",
				"누가 (S)의 (P)인가요?",
				"(O)가 (S)의 (P)가에요.",
				"영화 (S)는 누가 만들었나요?",
				"(S)를 지휘해서 만든 사람은 누구인가요?",
				"(S)의 (P)가름은 무엇인가요?",
				"(S)의 (P)를 맡은 사람이 누구일까요?",
				"(O)가 (S)의 (P)가에요.",
				"(S)의 (P)를 알려주세요.",
				"(S)는 (O)가라는 사람이 (P)가에요.",
				"(S)는 누가 (P)하였나요?",
				"(O)는 (S)의 (P)가에요.",
				"(S)를 지휘하며 촬영한 사람은 누구인가요?",
				"(S)를 지휘하며 촬영한 사람은 (O)가에요.",
				"(S)는 어느 (P)의 영화인가요?",
				"(S)는 (O)가 (P)했어요.",
				"(S)를 만든 사람은 누구인가요?",
				"(S)를 만든 사람은 (O)가에요.",
				"로봇소리를 만든 사람은 누구인가요?",
				"로봇소리를 만든 사람은 (O)에요.",
				"(S)는 누가 (P)했나요?",
				"(S)가 (P)한 영화예요.",
				"(S)를 만든 (P)는 누구인가요?",
				"(S)가라는 영화의 (P)는 누구인가요?",
				"(S)가라는 영화의 (P)는 (O)가에요.",
				"(S)는 누가 제작했나요?",
				"(S)는 (O)가 만들었어요.",
				"(S)를 제작한 (P)는 누구인가요?",
				"(S)를 제작한 (P)는 (O)가에요.",
				"(S)를 (P)한 사람은 누구인가요?",
				"(S)의 제작자는 누구인가요?",
				"(S)의 제작자는 (O)가에요.",
				"(O)가 (S)의 (P)가에요",
				"(S)는 누가 (P)하였나요?",
				"(S)는 (O)가 (P)했어요",
				"(S)를 만든 (P)는 누구인가요?",
				"(S)는 (O)(P)의 작품이에요.",
				"(S)를 만든 사람은 누구인가요?",
				"(S)를 만든 사람은 (O)(P)가에요.",
				"(S)는 (O)(P)의 작품이에요.",
				"(S)를 총 (P)한 사람은 누구인가요?",
				"(S)를 총 (P)한 사람은 (O)가에요.",
				"(S)를 지휘하며 촬영한 사람은 누구인가요?",
				"(S)는 어떤 (P)가 메가폰을 잡았나요?",
				"(O)가 (S)의 (P)가에요",
				"(S)는 누가 (P)하였나요?",
				"(O)는 (S)의 (P)가에요.",
				"누가 (S)를 (P)했나요?",
				"(O)(P)가 (S)를 만들었어요",
				"(S)를 만든 사람은 누구인가요?",
				"(S)를 만든 사람은 (O)가에요.",
				"영화 (S)를 만든 (P)가름은 무엇인가요?",
				"(S)라는 영화는 (O)(P)가 만들었어요",
				"(S)v의 (P)의 이름은 무엇인가요?",
				"(S)v의 (P)가름은 (O)라고 해요.",
				"(O)는 (S)의 (P)가에요.",
				"(S)를 만든 (P)는 누구인가요?",
				"(S)를 만든 (P)는 (O)에요",
				"(S)는 어느 (P)의 영화인가요?",
				"(S)의 모든것을 총괄한 사람은 누구인가요?",
				"(S)의 모든것을 총괄한 사람은 (O)가에요",
				"(S)는 누가 (P)했나요?",
				"(O)는 (S)의 (P)가에요",
				"(S)는 누가 (P)인가요?",
				"(O)가 (S)의 (P)가에요.",
				"(S)는 누가 (P)를 맡았나요?",
				"(O)가 (P)를 맡은 영화는 (S)가에요.",
				"(S)는 누가 디렉팅했나요?",
				"(O)가 (S)를 디렉팅했어요.",
				"(S)는 누가 (P)를 했나요?",
				"(S)를 (P)한 사람은 (O)예요.",
				"(S)는 누가 (P)하였나요?",
				"(S)는 (O)가 (P)가예요",
				"(S)의 (P)가 누군지 아시는지요?",
				"(S)의 (P)는 (O)가지요",
				"(S)의 (P)가름은 무엇인가요?",
				"(S)의 (P)가름은 (O)에요.",
				"(S) 의 (P)는 누구인가요?",
				"(S)의 (P)는 (O)가에요.",
				"(S)를 총지휘한 (P)는 누구인가요?",
				"(S)는 (O)가 (P)했어요.",
				"(S)는 누가 만들었나요?",
				"(O)는 (S)의 (P)가에요.",
				"(S)를 찍은 (P)는 누구예요?",
				"(S)의 (P)가 된 사람은 (O)예요.",
				"(S)를 만든 사람은 누구인가요?",
				"(S)는 (O)가 만들었어요.",
				"여자 정혜의 (P)를 누가했는지 알아요?",
				"여자 정혜를 찍은 (P)님은 (O)(P)님인 걸로 알고 있어요",
				"(S)는 누가 (P)했나요?",
				"(S)는 (O)(P)가 만들었어요",
				"(S)는 누가 (P)했나요?",
				"(S)는 (O)(P)가 만들었어요",
				"누가 (S)를 (P)했나요?",
				"(S)는 (O)가 (P)했어요",
				"누가 (S)의 (P)인가요?",
				"(O)가 (S)의 (P)가에요.",
				"(S)는 누가 제작했나요?",
				"(S)를 만든 사람은 (O)가에요.",
				"(S)를 (P)한 사람이 누구예요?",
				"(O)(P)가 (S)를 (P)했어요.",
				"(S)를 지휘해서 만든 사람은 누구인가요?",
				"(S)를 지휘해서 만든 사람은 (O)가에요.",
				"(S)를 제작한 (P)는 누구인가요?",
				"(S)를 제작한 (P)는 (O)에요.",
				"영화 중에 (S)의 (P)가 누군가요",
				"(S)의 (P)는 (O)가라고 하지요",
				"(S)가라는 제목의 영화를 만든 (P)는 누구인가요?",
				"(S)가라는 제목의 영화를 만든 (P)는 (O)가에요.",
				"(S)는 (O)(P)의 작품이라고 해요",
				"(S)를 연출한 사람은 누구인가요?",
				"(S)의 (P)를 맡은 사람은 (O)가에요.",
				"여자 정혜의 (P)는 누구에요?",
				"여자 정혜의 (P)는 (O)에요.",
				"누가 (S)를 (P)했나요?",
				"(S)는 (O)가 (P)했어요.",
				"(S)를 만든 사람은 누구인가요?",
				"누가 (S)를 (P)했나요?",
				"(O)(P)가 (S)를 (P)했어요.",
				"(S)의 (P)를 누가했나요?",
				"(O)는 (S)를 (P)했어요",
				"Captain America: The Winter Soldier를 제작한 (P)는 누구에요?",
				"(S)를 제작한 (P)는 (O)에요.",
				"(S)를 (P)한 인물은 누구인가요?",
				"(S)영화의 (P)직을 맡은 인물은 (O)에요",
				"(S)에서 (P)를 누구 맡았나요?",
				"(S)에서 (P)를 맡은 인물은 (O)가에요",
				"(S)(P)의 이름은 무엇인가요?",
				"(S)는 (O)(P)의 작품이라고 해요",
				"(S)의 (P)는 어떻게 되요?",
				"(O)는 (S)의 (P)가예요.",
				"누가 (S)를 (P)했나요?",
				"(O)(P)가 (S)를 만들었어요",
				"누가 (S)의 (P)인가요?",
				"(S)는 (O)가 (P)가에요.",
				"(S)를 연출한 사람은 누구인가요?",
				"(S)를 만든 사람은 누구인가요?",
				"(S)는 누구의 지휘아래 만들어졌나요?",
				"(S)는 (O)가 (P)했어요",
				"(S)를 만든 사람은 누구인가요?",
				"(S)(P)는 누구예요?",
				"(S)의 (P)는 (O)가예요.",
				"2008년 영화 (S)를 만든 사람은 누구인가요?",
				"2008년 영화 (S)를 만든 사람은 (O)가에요.",
				"(S)를 만든 (P)의 이름은 무엇인가요?",
				"(S)를 만든 (P)의 이름은 (O)가에요.",
				"(S)의 연출이 누구에요?",
				"(S)는 (O)가 만들었어요",
				"(S)는 누가 만들었나요?",
				"(S)의 (P)를 알려주세요.",
				"(O)가라는 사람이 (S)를 (P)했어요.",
				"(S)는 누가 만들었어요?",
				"(S)는 (O)가 만들었어요",
				"(S)는 누가 총 지휘했나요?",
				"(O)가 (S)를 (P)했어요.",
				"(S)를 만든사람은 누구인가요?",
				"(O)(P)는 (S)를 만들었어요",
				"(S)의 (P)의 이름은 무엇인가요?",
				"(S)는 누가 만들었나요?",
				"(S)는 (O)(P)가 만들었어요",
				"(S)의 (P)의 이름은 무엇인가요?",
				"(S)는 누가 연출했나요?",
				"(S)는 (O)가 연출했어요.",
				"(S)를 제작한 (P)는 누구인가요?",
				"(S)를 제작한 (P)는 (O)가에요.",
				"(S)는 어떤 (P)가 연출했나요?",
				"(S)의 연출은 (O)가 맡았어요.",
				"(S)를 지휘해서 만든 사람은 누구인가요?",
				"(S)를 지휘해서 만든 사람은 (O)가에요.",
				"영화 (S)는 누가 만들었나요?",
				"(S)라는 영화는 (O)가 만들었어요.",
				"(S)에서 메가폰을 잡은 사람은 누군가요?",
				"(S)에서 메가폰을 잡은 사람은 (O)가에요.",
				"(S)를 지휘하며 촬영한 사람은 누구인가요?",
				"(S)를 지휘하며 촬영한 사람은 (O)에요.",
				"(S)의 (P)를 담당한 사람은 누구인가요?",
				"(S)의 (P)가름은 (O)에요.",
				"(S)의 연출자는 (O)가에요.",
				"어떤 사람이 (S)의 (P)인가요?",
				"(O)는 (S)의 (P)가에요.",
				"(S)는 누가 (P)했나요?",
				"(S)는 누가 (P)했나요?",
				"(O)는 (S)의 (P)가에요.",
				"(S)는 누가 연출을 맡았나요?",
				"(S)의 연출을 맡은 사람은 (O)가에요.",
				"(S)를 연출한 사람은 누구인가요?",
				"(S)의 연출자는 (O)가에요.",
				"(S)는 누가 (P)를 했나요?",
				"(S)는 (O)가 (P)를 맡았어요.",
				"(S)를 만든 사람은 누구인가요?",
				"(S)라는 (O)가 만든 영화에요.",
				"(S)는 누가 지휘해서 만들었나요?",
				"(S)를 지휘해서 만든 사람은 (O)에요.",
				"(S)를 만든 사람은 누구인가요?",
				"(S)를 만든 사람은 (O)가에요.",
				"(S)의 제작자는 누구인가요?",
				"(S)의 제작자는 (O)가에요.",
				"누가 (S)를 연출했나요?",
				"(S)를 연출한 사람은 (O)에요.",
				"어떤 사람이 (S)의 (P)인가요?",
				"(O)(P)가 (S)의 (P)가에요.",
				"(S)를 만든 사람은 누구인가요?",
				"(S)는 누가 (P)인가요?",
				"(O)가 (S)의 (P)가에요.",
				"(S)는 누가 (P)했나요?",
				"(O)가 (S)를 (P)했어요.",
				"(S)는 어느 (P)가 만들었나요?",
				"(O)(P)가 (S)를 만들었어요.",
				"(S)는 누가 만들었어요?",
				"(S)는 (O)가 만들었어요",
				"(S)를 연출한 사람은 누구인가요?",
				"(O)가 (S)를 연출했어요.",
				"(S)는 어느 (P)의 작품인가요?",
				"(O)는 (S)의 (P)가라고 해요",
				"(S)는 누가 만들었나요?",
				"(S)는 (O)(P)가 만들었어요.",
				"(S)는 어느 (P)의 영화인가요?",
				"(O)(P)의 영화는 (S)예요.",
				"(S)는 어떤 사람이 만들었나요?",
				"(O)가 (S)를 제작했어요.",
				"누가 (S)를 연출했나요?",
				"(O)가 (S)를 연출했어요.",
				"(S)에서 (P)직은 누가 맡았나요?",
				"(S)의 (P)직을 (O)가 맡았어요",
				"(S)의 (P)는 누구예요?",
				"(S)의 (P)는 (O)가예요.",
				"(S)는 누가 만들었나요?",
				"(S)는 (O)(P)가 만들었어요",
				"(S)는 누가 연출했나요?",
				"(S)는 (O)가 연출했어요.",
				"(S)를 지휘해서 만든 사람은 (O)에요.",
				"(S)를 만든 사람은 누구인가요?",
				"(S)를 만든 사람은 (O)가에요.",
				"(S)의 연출가는 누구인가요?",
				"(S)의 연출가는 (O)에요.",
				"(S)의 촬영을 지휘한 사람이 누구인가요?",
				"(O)(P)가 (S)의 촬영을 지휘했어요.",
				"(S)는 누가 (P)했나요?",
				"(S)는 (O)가 (P)했어요.",
				"(S)를 만든 사람은 누구인가요?",
				"(S)를 만든 사람은 (O)가에요.",
				"(S)는 누가 제작했나요?",
				"(S)를 만든 사람은 (O)가에요.",
				"(S)2011년 영화는 누가 만들었나요?",
				"(S)2011년 영화를 만든 사람은 (O)가에요.",
				"영화 (S)의 (P)를 누가 맡았나요?",
				"영화 (S)는 (O)가 (P)를 맡았어요.",
				"누가 (S)를 연출했나요?",
				"(O)가 (S)를 연출했어요.",
				"(S)의 (P)의 이름을 적어주세요.",
				"(S)의 (P)가름은 (O)에요.",
				"(S)는 누구의 작품인가요?",
				"(O)(P)가 (S)를 찍었어요.",
				"(S)를 만든 (P)의 이름은 무엇인가요?",
				"(S)를 만든 (P)의 이름은 (O)가에요.",
				"어떤 사람이 (S)의 (P)인가요?",
				"(O)는 (S)의 (P)가에요.",
				"(S)(P)의 이름이 어떻게 되나요?",
				"(S)(P)의 이름은 (O)가에요.",
				"(S)를 만든 (P)는 누구인가요?",
				"(S)는 (O)(P)의 작품이에요.",
				"영화 (S)의 (P)가 누군지 아시나요?",
				"영화 (S)의 (P)는 (O)가에요",
				"누가 (S)의 (P)인가요?",
				"(O)가 (S)의 (P)가에요.",
				"(S)의 (P)의 이름은 무엇인가요?",
				"(O)는 (S)의 (P)가라고 해요",
				"영화 (S)는 어떤 (P)가 제작했나요?",
				"(O)(P)는 (S)를 제작했어요.",
				"(O)(P)가 (S)를 만들었어요.",
				"(S)는 누가 (P)했나요?",
				"(S)는 누가 (P)했나요?",
				"(S)는 (O)가 (P)했어요.",
				"어떤 사람이 (S)의 (P)인가요?",
				"(O)는 (S)의 (P)가에요.",
				"(S)를 제작한 (P)는 누구인가요?",
				"(S)를 제작한 (P)는 (O)가에요.",
				"(S)는 누가 (P)를 했나요?",
				"(S)는 (O)가 (P)한거예요.",
				"(S)를 만든 사람은 누구인가요?",
				"(S)를 만든 사람은 (O)가에요.",
				"DMZ 비무장지대의 (P)를 맡은 사람은 누구인가요?",
				"DMZ비무장지대의 (P)를 맡은 사람은 (O)가에요",
				"(S)는 어느 (P)의 작품인가요?",
				"(O)는 (S)의 (P)가라고 해요",
				"(S)는 누가 (P)인가요?",
				"(S)는 (O)가 (P)해요",
				"어떤 사람이 (S)의 (P)인가요?",
				"(O)는 (S)의 (P)가에요.",
				"(S)를 총 (P)한 사람은 누구인가요?",
				"(S)를 총 (P)한 사람은 (O)가에요.",
				"(S)를 (P)한 사람은 누구인가요?",
				"(S)를 (P)한 사람은 (O)가예요.",
				"(S)는 어떤 (P)의 작품인가요?",
				"(S)는 (O)(P)가 찍었어요.",
				"(S)를 (P)한 사람은 누구인가요?",
				"(S)를 (P)한 사람은 (O)가예요.",
				"(S)를 (P)한 사람은 누구인가요?",
				"(S)를 (P)한 사람은 (O)가에요.",
				"누가 (S)의 (P)인가요?",
				"(O)가 (S)의 (P)가에요.",
				"(S)는 누가 만들었나요?",
				"(O)가 (S)를 연출했어요.",
				"(S)를 만든 사람은 누구인가요?",
				"(O)가 (S)를 (P)했어요",
				"(S)를 총괄하고 책임진 사람은 누구인가요?",
				"(S)를 총괄하고 책임진 사람은 (O)에요.",
				"(S)를 제작한 (P)는 누구인가요?",
				"(S)는 (O)(P)에 의해 제작되었어요.",
				"(S)의 (P)가름은 (O)에요.",
				"누가 (S)를 (P)했나요?",
				"(S)는 (O)가 (P)했어요.",
				"(S)의 (P)는 누구예요?",
				"(S)의 (P)는 (O)가예요.",
				"(S)는 누가 (P)했나요?",
				"(S)의 (P)는 이옥섭구교환강경태윤성호 예요.",
				"(S)는 누가 (P)했나요?",
				"(S)는 (O)가 (P)한 작품이에요.",
				"(S)의 디렉터는 누구인가요?",
				"(S)의 (P)의 이름은 무엇인가요?",
				"(S)를 제작한 김독의 이름은 (O)가예요.",
				"누가 (S)를 (P)했나요?",
				"(S)는 (O)가 (P)했어요",
				"(S)v의 (P)의 이름을 답해주세요.",
				"(S)v를 만든 (P)는 (O)에요.",
				"(S)는 누가 (P)했나요?",
				"(S)연출자는 (O)가에요.",
				"(S)는 누구의 작품인가요?",
				"(S)는 (O)(P)가 만들었어요",
				"애니메이션 (S)의 (P)가 누구인가요?",
				"(S)는 (O)가 (P)가에요.",
				"(S)를 제작한 (P)는 누구인가요?",
				"(S)를 제작한 (P)는 (O)가에요.",
				"(S)라는 영화를 제작한 이는 누구인가요?",
				"(S)라는 영화를 제작한 이는 (O)에요.",
				"(S)를 제작한 (P)는 누구인가요?",
				"(S)를 제작한 (P)는 (O)가에요.",
				"(S)는 어떤 사람의 작품인가요?",
				"(S)를 만든 (P)는 (O)라는 사람이에요.",
				"(S)는 누구의 작품인가요?",
				"(S)는 (P)(O)의 작품이에요.",
				"(S)는 어느 (P)의 영화인가요?",
				"(S)는 신수원 홍지영 이수연 김성호가 (P)를 맡은 영화라고 해요",
				"(S)를 (P)한 사람의 이름은 무엇인가요?",
				"(S)(P)를 한 사람은 (O)가에요",
				"(S)를 제작한 사람은 누구인가요?",
				"(S)의 메가폰을 잡은 사람은 누구인가요?",
				"(O)(P)가 (S)의 메가폰을 잡았어요.",
				"(S)를 (P)한 사람은 어떤 사람이 (P)했을까요?",
				"(O)(P)가 (S)를 (P)했어요.",
				"(S)의 (P)가름은 (O)에요.",
				"(S)는 누가 연출했나요?",
				"(S)는 (O)연출이 만들었어요.",
				"(S)의 (P)가름을 쓰세요.",
				"(S)의 (P)가름은 (O)에요.",
				"(S)의 디렉터는 누구인가요?",
				"(S)는 어떤 사람이 (P)를 맡았나요?",
				"(O)(P)가 (S)를 만들었어요.",
				"(S)의 디렉터는 누구인가요?",
				"(S)는 (O)가 (P)한 작품이에요",
				"2014년 영화 (S)는 누가 (P)했나요?",
				"2014년 영화 (S)는 (O)가 (P)가에요.",
				"누가 (S)를 (P)했나요?",
				"(S)는 (O)가 (P)했어요",
				"(S)의 (P)를 담당한 사람은 누구인가요?",
				"(S)는 (O)가 (P)를 했어요.",
				"(S)는 누가 연출했나요?",
				"(S)는 (O)가 연출했어요.",
				"(S)는 (O)(P)의 작품이에요.",
				"(S)의 제작을 총괄하신분은 누구인가요?",
				"(S)를 총괄한 분은 (O)가에요.",
				"영화 (S)는 누가 만들었나요?",
				"(S)의 (P)가름은 (O)가라고 해요",
				"DMZ비무장지대를 연출한 사람은 누구예요?",
				"DMZ비무장지대를 연출한 (P)는 (O)가에요",
				"(S)의 디렉터는 누구인가요?",
				"(S)는 (O)에의해 만들어졌어요",
				"(S)의 디렉터는 누구인가요?",
				"(S)의 디렉터는 (O)에요",
				"(S)는 누가 지휘해서 만들었나요?",
				"(S)는 (O)가 지휘해서 만들었어요.",
				"누가 (S)를 (P)했나요?",
				"(S)는 (O)가 (P)했어요",
				"누가 (S)의 (P)를 맡았나요?",
				"(O)가 (S)를 (P)했어요.",
				"누가 (S)를 (P)했나요?",
				"(S)는 (O)가 (P)했어요.",
				"누가 (S)의 (P)인가요?",
				"(O)가 (S)의 (P)가에요.",
				"(S)는 누가 (P)한 영화인가요?",
				"(O)는 (S)의 (P)가에요.",
				"(S)는 (O)가 만들었어요.",
				"(S)를 제작한 (P)는 누구에요?",
				"(S)를 제작한 (P)는 (O)가에요.",
				"(S)는 어느 (P)의 작품인가요?",
				"(S)는 (O)(P)의 작품이라고 해요",
				"(S)2008년 영화는 누가 만들었나요?",
				"(S)2008년 영화는 (O)가 만들었어요.",
				"(S)의 (P)님의 성함은 무엇인가요?",
				"(S)를 만든 사람 이름은 (O)가에요",
				"(S)(1984년 영화은 누가 연출했나요?",
				"(S)의 연출자는 (O)가에요.",
				"어떤 (P)가 (S)를 만들었나요?",
				"(S)(P)가름은 (O)가에요",
				"(S)를 만든사람은 누구인가요?",
				"(O)(P)는 (S)를 만들었어요",
				"(S)를 총 (P)한 사람은 누구인가요?",
				"(S)를 총 (P)한 사람은 (O)가에요.",
				"누가 (S)의 (P)인가요?",
				"(O)가 (S)의 (P)가에요.",
				"(S)의 제작자는 누구인가요?",
				"(S)의 제작자는 (O)가에요.",
				"(S)는 누가 (P)했나요?",
				"(O)는 (S)의 (P)가에요.",
				"(S)의 제작자는 누구인가요?",
				"(S)의 제작자는 (O)가에요.",
				"(S)는 누가 (P)를 맡았나요?",
				"(S)는 (O)가 (P)를 맡았어요.",
				"(S)의 (P)가름은 무엇이에요?",
				"(S)의 (P)가름은 (O)에요.",
				"(S)는 누가 지휘해서 만들었나요?",
				"(S)를 지휘해서 만든 사람은 (O)에요.",
				"영화 (S)를 (P)한 사람의 이름은 무엇인가요?",
				"영화 (S)를 (P)한 사람의 이름은 (O)가에요.",
				"(S)를 만든사람은 누구인가요?",
				"(O)(P)는 (S)를 만들었어요",
				"(S)의 디렉터가 누구인가요?",
				"(S)를 총괄한 사람은 (O)가에요.",
				"누가 (S)를 (P)했나요?",
				"(S)는 누가 (P)했나요?",
				"(O)는 (S)의 (P)가에요",
				"영화 (S)를 제작한 사람은 누구인가요?",
				"영화 (S)를 제작한 사람은 (O)에요.",
				"(S)는 누가 지휘해서 만들었나요?",
				"(S)를 지휘해서 만든 사람은 (O)에요.",
				"(S)의 (P)는 어떻게 되요?",
				"(O)는 (S)의 (P)가예요.",
				"누가 (S)라는 영화를 만들었나요?",
				"김상민은 (S)라는 영화를 만들었어요.",
				"(S)의 (P)는 어떻게 되요?",
				"(O)는 (S)의 (P)가예요.",
				"(S)는 누가 (P)하였나요?",
				"(S)는 (O)가 (P)했어요",
				"영화 (S)의 (P)는 누구인가요?",
				"영화 (S)의 (P)는 (O)가에요.",
				"(S)는 어느 (P)의 영화인가요?",
				"(S)의 (P)는 강경태 구교환이옥섭윤성호 예요.",
				"(S)는 어느 (P)가 만들었나요?",
				"(S)는 (O)(P)가 만들었어요.",
				"(S)제작을 총괄해서 맡은 사람은 누구인가요?",
				"(S)에서 (O)는 (P)를 맡았어요.",
				"영화 (S)(P)가 누군지 아시는지요?",
				"영화 (S)의 (P)는 (O)라네요",
				"(S)는 누가 총 지휘했나요?",
				"(O)가 (S)의 (P)를 맡았어요.",
				"누가 (S)의 (P)인가요?",
				"(S)는 (O)가 (P)했어요.",
				"(S)를 만든 사람은 누구인가요?",
				"(S)를 만든 사람은 (O)가에요.",
				"(S)를 (P)한 사람은 누구인가요?",
				"(S)를 (P)한 사람은 (O)가에요.",
				"누가 (S)의 (P)인가요?",
				"(O)가 (S)의 (P)가예요",
				"(S)라는 2011년 영화를 만든 사람은 누구인가요?",
				"(S)라는 2011년 영화는 (O)가 만들었어요.",
				"누가 (S)를 (P)했나요?",
				"(S)는 (O)가 (P)했어요.",
				"(S)(P)가름은 무엇이에요?",
				"(S)의 (P)가름은 (O)가에요.",
				"(S)의 (P)를 알고 싶어요.",
				"(O)가 (S)를 (P)했어요.",
				"(S)의 (P)를 담당한 사람은 누구인가요?",
				"(S)는 (O)가 (P)를 맡았어요.",
				"(S)를 만든 사람은 누구에요?",
				"(S)를 만든 사람은 (O)가에요",
				"(S)는 누가 (P)했나요?",
				"(S)는 (O)라는 사람이 (P)했어요.",
				"(S)는 누가 연출했나요?",
				"(S)는 (O)가 연출했어요.",
				"(S)의 (P)의 이름은 무엇인가요?",
				"신수원 홍지영 이수연 김성호는 (S)의 (P)가라고 해요",
				"(S)는 누가 만들었나요?",
				"(S)의 연출가는 (O)에요.",
				"(S)(P)는 누가 맡았나요?",
				"(S)(P)는 (O)가 맡았어요.",
				"(S)를 만든 사람은 누구인가요?",
				"(S)는 (O)가 만들었어요.",
				"(S)를 (P)한 사람은 누구인가요?",
				"(S)를 (P)한 사람은 (O)에요.",
				"누가 (S)의 (P)를 맡았나요?",
				"(S)의 (P)는 누가 맡았을까요?",
				"신아가 이상철은 (S)의 (P)가에요.",
				"(S)를 지휘하여 촬영한 사람은 누구인가요?",
				"(S)를 지휘하여 촬영한 사람은 (O)가에요",
				"(S)를 찍은 (P)는 누구인가요?",
				"(S)는 (O)(P)의 작품이에요.",
				"(S)는 누가 (P)했나요?",
				"(S)는 (O)(P)의 영화예요.",
				"(S)에서 (P)를 맡은 인물은 누구인가요?",
				"영화 (S)에서 (O)가 (P)를 맡았어요",
				"누가 (S)의 (P)를 맡았나요?",
				"(O)가 (S)를 총 지휘했어요.",
				"누가 (S)의 (P)인가요?",
				"(S)는 (O)가 (P)가에요.",
				"(S)를 (P)한 사람은 누구였나요?",
				"(S)((S)O(S))(S)를(S) (S)((S)P(S))(S)했(S)어(S)요(S).(S)",
				"(S)를 제작한 (P)는 누구인가요?",
				"(S)를 제작한 (P)는 (O)가에요.",
				"(S)를 만든 사람은 누구인가요?",
				"(S)를 만든 사람은 (O)에요.",
				"(S)는 누가 (P)하였나요?",
				"(S)는 (O)가 (P)했어요",
				"(S)는 누가 만들었나요?",
				"(S)가 만들었어요.",
				"(S)의 (P)는 누가 했나요?",
				"(S)에서 (P)를 한 사람은 (O)가에요.",
				"(S)를 누가 진두지휘 하셨나요?",
				"(S)를 진두지휘 한 사람은 (O)예요",
				"누가 (S)의 (P)인가요?",
				"(O)가 (S)의 (P)가에요.",
				"(S)는 누가 (P)를 맡았나요?",
				"(S)는 (O)가 (P)를 맡았어요.",
				"(S)를 만든 사람은 누구인가요?",
				"(S)을 만든 사람은 (O)(P)가에요.",
				"(S)를 총 지휘한 사람의 이름은 무엇인가요?",
				"(S)를 총 지휘한 사람의 이름은 (O)예요.",
				"(S)의 (P)를 맡은 사람은 누구인가요?",
				"(S)는 (O)가 (P)를 맡았어요.",
				"(S)는 어느 (P)의 작품이에요?",
				"(S)는 (O)(P)의 작품이에요.",
				"(S)를 만든 (P)의 이름은 누구일까요?",
				"(S)를 만든 (P)는 (O)라고 해요."
			],
			"banned": [],
			"elements_not_recognized": [
				"여자 정혜의 (P)는 누구에요?",
				"여자 정혜의 (P)는 (O)에요.",
				"(O)를 총 지휘했어요.",
				"로봇소리의 제작 과정을 책임진 사람은 누구인가요?",
				"로봇소리의 제작과정을 책임진 사람은 (O)에요.",
				"여자 정혜의 (P)를 누가했는지 알아요?",
				"여자 정혜를 찍은 (P)님은 (O)(P)님인 걸로 알고 있어요",
				"로봇소리를 만든 사람은 누구인가요?",
				"로봇소리를 만든 사람은 (O)에요.",
				"Captain America: The Winter Soldier를 제작한 (P)는 누구에요?",
				"DMZ 비무장지대의 (P)를 맡은 사람은 누구인가요?",
				"DMZ비무장지대의 (P)를 맡은 사람은 (O)가에요",
				"(O)를 총 지휘했어요.",
				"로봇소리를 만든 사람은 누구인가요?",
				"로봇소리를 만든 사람은 (O)에요.",
				"여자 정혜의 (P)를 누가했는지 알아요?",
				"여자 정혜를 찍은 (P)님은 (O)(P)님인 걸로 알고 있어요",
				"여자 정혜의 (P)는 누구에요?",
				"여자 정혜의 (P)는 (O)에요.",
				"Captain America: The Winter Soldier를 제작한 (P)는 누구에요?",
				"DMZ 비무장지대의 (P)를 맡은 사람은 누구인가요?",
				"DMZ비무장지대의 (P)를 맡은 사람은 (O)가에요",
				"DMZ비무장지대를 연출한 사람은 누구예요?",
				"DMZ비무장지대를 연출한 (P)는 (O)가에요",
				"DMZ비무장지대를 연출한 사람은 누구예요?",
				"DMZ비무장지대를 연출한 (P)는 (O)가에요"
			]
		}
	}
}